task2/counter.sv
module counter #(
    parameter WIDTH = 8
)(
    input logic                 clk,    // clock (duh)
    input logic                 rst,    // reset
    input logic                 en,     // count direction
    output logic[WIDTH-1:0]     count   // count output
);

always_ff @(posedge clk, posedge rst) // CHALLENGE asynchronous reset
    if (rst) count <= {WIDTH{1'b0}};
    else count <= count + ((-1)**(en+1))*{{WIDTH-1{1'b0}}, 1}; // could be rewrittn with a mux? also why the brackets around the first arg

endmodule

task2/counter.vcd
$version Generated by VerilatedVcd $end
$date Sun Oct 22 11:02:44 2023 $end
$timescale 1ps $end

 $scope module TOP $end
  $var wire  1 # clk $end
  $var wire  8 & count [7:0] $end
  $var wire  1 % en $end
  $var wire  1 $ rst $end
  $scope module counter $end
   $var wire 32 ' WIDTH [31:0] $end
   $var wire  1 # clk $end
   $var wire  8 & count [7:0] $end
   $var wire  1 % en $end
   $var wire  1 $ rst $end
  $upscope $end
 $upscope $end
$enddefinitions $end


#0
1#
1$
0%
b00000000 &
b00000000000000000000000000001000 '
#1
0#
#2
1#
1%
#3
0#
#4
1#
#5
0#
#6
1#
0$
#7
0#
#8
1#
b00000001 &
#9
0#
#10
1#
b00000010 &
#11
0#
#12
1#
b00000011 &
#13
0#
#14
1#
b00000100 &
#15
0#
#16
1#
b00000101 &
#17
0#
#18
1#
b00000110 &
#19
0#
#20
1#
b00000111 &
#21
0#
#22
1#
b00001000 &
#23
0#
#24
1#
b00001001 &
#25
0#
#26
1#
b00001010 &
#27
0#
#28
1#
b00001011 &
#29
0#
#30
1#
b00001100 &
#31
0#
#32
1#
1$
b00001101 &
#33
0#
b00000000 &
#34
1#
0$
#35
0#
#36
1#
b00000001 &
#37
0#
#38
1#
b00000010 &
#39
0#
#40
1#
b00000011 &
#41
0#
#42
1#
b00000100 &
#43
0#
#44
1#
b00000101 &
#45
0#
#46
1#
b00000110 &
#47
0#
#48
1#
b00000111 &
#49
0#
#50
1#
b00001000 &
#51
0#
#52
1#
b00001001 &
#53
0#
#54
1#
b00001010 &
#55
0#
#56
1#
b00001011 &
#57
0#
#58
1#
b00001100 &
#59
0#
#60
1#
b00001101 &
#61
0#
#62
1#
b00001110 &
#63
0#
#64
1#
b00001111 &
#65
0#
#66
1#
b00010000 &
#67
0#
#68
1#
b00010001 &
#69
0#
#70
1#
b00010010 &
#71
0#
#72
1#
b00010011 &
#73
0#
#74
1#
b00010100 &
#75
0#
#76
1#
b00010101 &
#77
0#
#78
1#
b00010110 &
#79
0#
#80
1#
b00010111 &
#81
0#
#82
1#
b00011000 &
#83
0#
#84
1#
b00011001 &
#85
0#
#86
1#
b00011010 &
#87
0#
#88
1#
b00011011 &
#89
0#
#90
1#
b00011100 &
#91
0#
#92
1#
b00011101 &
#93
0#
#94
1#
b00011110 &
#95
0#
#96
1#
b00011111 &
#97
0#
#98
1#
b00100000 &
#99
0#
#100
1#
b00100001 &
#101
0#
#102
1#
b00100010 &
#103
0#
#104
1#
b00100011 &
#105
0#
#106
1#
b00100100 &
#107
0#
#108
1#
b00100101 &
#109
0#
#110
1#
b00100110 &
#111
0#
#112
1#
b00100111 &
#113
0#
#114
1#
b00101000 &
#115
0#
#116
1#
b00101001 &
#117
0#
#118
1#
b00101010 &
#119
0#
#120
1#
b00101011 &
#121
0#
#122
1#
b00101100 &
#123
0#
#124
1#
b00101101 &
#125
0#
#126
1#
b00101110 &
#127
0#
#128
1#
b00101111 &
#129
0#
#130
1#
b00110000 &
#131
0#
#132
1#
b00110001 &
#133
0#
#134
1#
b00110010 &
#135
0#
#136
1#
b00110011 &
#137
0#
#138
1#
b00110100 &
#139
0#
#140
1#
b00110101 &
#141
0#
#142
1#
b00110110 &
#143
0#
#144
1#
b00110111 &
#145
0#
#146
1#
b00111000 &
#147
0#
#148
1#
b00111001 &
#149
0#
#150
1#
0%
b00111010 &
#151
0#
#152
1#
b00111001 &
#153
0#
#154
1#
b00111000 &
#155
0#
#156
1#
b00110111 &
#157
0#
#158
1#
b00110110 &
#159
0#
#160
1#
b00110101 &
#161
0#
#162
1#
b00110100 &
#163
0#
#164
1#
b00110011 &
#165
0#
#166
1#
b00110010 &
#167
0#
#168
1#
b00110001 &
#169
0#
#170
1#
b00110000 &
#171
0#
#172
1#
b00101111 &
#173
0#
#174
1#
b00101110 &
#175
0#
#176
1#
b00101101 &
#177
0#
#178
1#
b00101100 &
#179
0#
#180
1#
b00101011 &
#181
0#
#182
1#
b00101010 &
#183
0#
#184
1#
b00101001 &
#185
0#
#186
1#
b00101000 &
#187
0#
#188
1#
b00100111 &
#189
0#
#190
1#
b00100110 &
#191
0#
#192
1#
b00100101 &
#193
0#
#194
1#
b00100100 &
#195
0#
#196
1#
b00100011 &
#197
0#
#198
1#
b00100010 &
#199
0#
#200
1#
b00100001 &
#201
0#
#202
1#
b00100000 &
#203
0#
#204
1#
b00011111 &
#205
0#
#206
1#
b00011110 &
#207
0#
#208
1#
b00011101 &
#209
0#
#210
1#
b00011100 &
#211
0#
#212
1#
b00011011 &
#213
0#
#214
1#
b00011010 &
#215
0#
#216
1#
b00011001 &
#217
0#
#218
1#
b00011000 &
#219
0#
#220
1#
b00010111 &
#221
0#
#222
1#
b00010110 &
#223
0#
#224
1#
1%
b00010101 &
#225
0#
#226
1#
b00010110 &
#227
0#
#228
1#
b00010111 &
#229
0#
#230
1#
b00011000 &
#231
0#
#232
1#
b00011001 &
#233
0#
#234
1#
b00011010 &
#235
0#
#236
1#
b00011011 &
#237
0#
#238
1#
b00011100 &
#239
0#
#240
1#
b00011101 &
#241
0#
#242
1#
b00011110 &
#243
0#
#244
1#
b00011111 &
#245
0#
#246
1#
b00100000 &
#247
0#
#248
1#
b00100001 &
#249
0#
#250
1#
b00100010 &
#251
0#
#252
1#
b00100011 &
#253
0#
#254
1#
b00100100 &
#255
0#
#256
1#
b00100101 &
#257
0#
#258
1#
b00100110 &
#259
0#
#260
1#
b00100111 &
#261
0#
#262
1#
b00101000 &
#263
0#
#264
1#
b00101001 &
#265
0#
#266
1#
b00101010 &
#267
0#
#268
1#
b00101011 &
#269
0#
#270
1#
b00101100 &
#271
0#
#272
1#
b00101101 &
#273
0#
#274
1#
b00101110 &
#275
0#
#276
1#
b00101111 &
#277
0#
#278
1#
b00110000 &
#279
0#
#280
1#
b00110001 &
#281
0#
#282
1#
b00110010 &
#283
0#
#284
1#
b00110011 &
#285
0#
#286
1#
b00110100 &
#287
0#
#288
1#
b00110101 &
#289
0#
#290
1#
b00110110 &
#291
0#
#292
1#
b00110111 &
#293
0#
#294
1#
b00111000 &
#295
0#
#296
1#
b00111001 &
#297
0#
#298
1#
b00111010 &
#299
0#
#300
1#
b00111011 &
#301
0#
#302
1#
b00111100 &
#303
0#
#304
1#
b00111101 &
#305
0#
#306
1#
b00111110 &
#307
0#
#308
1#
b00111111 &
#309
0#
#310
1#
b01000000 &
#311
0#
#312
1#
b01000001 &
#313
0#
#314
1#
b01000010 &
#315
0#
#316
1#
b01000011 &
#317
0#
#318
1#
b01000100 &
#319
0#
#320
1#
b01000101 &
#321
0#
#322
1#
b01000110 &
#323
0#
#324
1#
b01000111 &
#325
0#
#326
1#
b01001000 &
#327
0#
#328
1#
b01001001 &
#329
0#
#330
1#
b01001010 &
#331
0#
#332
1#
b01001011 &
#333
0#
#334
1#
b01001100 &
#335
0#
#336
1#
b01001101 &
#337
0#
#338
1#
b01001110 &
#339
0#
#340
1#
b01001111 &
#341
0#
#342
1#
b01010000 &
#343
0#
#344
1#
b01010001 &
#345
0#
#346
1#
b01010010 &
#347
0#
#348
1#
b01010011 &
#349
0#
#350
1#
b01010100 &
#351
0#
#352
1#
b01010101 &
#353
0#
#354
1#
b01010110 &
#355
0#
#356
1#
b01010111 &
#357
0#
#358
1#
b01011000 &
#359
0#
#360
1#
b01011001 &
#361
0#
#362
1#
b01011010 &
#363
0#
#364
1#
0%
b01011011 &
#365
0#
#366
1#
b01011010 &
#367
0#
#368
1#
b01011001 &
#369
0#
#370
1#
b01011000 &
#371
0#
#372
1#
b01010111 &
#373
0#
#374
1#
b01010110 &
#375
0#
#376
1#
b01010101 &
#377
0#
#378
1#
b01010100 &
#379
0#
#380
1#
b01010011 &
#381
0#
#382
1#
b01010010 &
#383
0#
#384
1#
b01010001 &
#385
0#
#386
1#
b01010000 &
#387
0#
#388
1#
b01001111 &
#389
0#
#390
1#
b01001110 &
#391
0#
#392
1#
b01001101 &
#393
0#
#394
1#
b01001100 &
#395
0#
#396
1#
b01001011 &
#397
0#
#398
1#
b01001010 &
#399
0#
#400
1#
1%
b01001001 &
#401
0#
#402
1#
b01001010 &
#403
0#
#404
1#
b01001011 &
#405
0#
#406
1#
b01001100 &
#407
0#
#408
1#
b01001101 &
#409
0#
#410
1#
b01001110 &
#411
0#
#412
1#
b01001111 &
#413
0#
#414
1#
b01010000 &
#415
0#
#416
1#
b01010001 &
#417
0#
#418
1#
b01010010 &
#419
0#
#420
1#
b01010011 &
#421
0#
#422
1#
b01010100 &
#423
0#
#424
1#
b01010101 &
#425
0#
#426
1#
b01010110 &
#427
0#
#428
1#
b01010111 &
#429
0#
#430
1#
b01011000 &
#431
0#
#432
1#
b01011001 &
#433
0#
#434
1#
b01011010 &
#435
0#
#436
1#
b01011011 &
#437
0#
#438
1#
b01011100 &
#439
0#
#440
1#
b01011101 &
#441
0#
#442
1#
b01011110 &
#443
0#
#444
1#
b01011111 &
#445
0#
#446
1#
b01100000 &
#447
0#
#448
1#
b01100001 &
#449
0#
#450
1#
b01100010 &
#451
0#
#452
1#
b01100011 &
#453
0#
#454
1#
b01100100 &
#455
0#
#456
1#
b01100101 &
#457
0#
#458
1#
b01100110 &
#459
0#
#460
1#
b01100111 &
#461
0#
#462
1#
b01101000 &
#463
0#
#464
1#
b01101001 &
#465
0#
#466
1#
b01101010 &
#467
0#
#468
1#
b01101011 &
#469
0#
#470
1#
b01101100 &
#471
0#
#472
1#
b01101101 &
#473
0#
#474
1#
b01101110 &
#475
0#
#476
1#
b01101111 &
#477
0#
#478
1#
b01110000 &
#479
0#
#480
1#
b01110001 &
#481
0#
#482
1#
b01110010 &
#483
0#
#484
1#
b01110011 &
#485
0#
#486
1#
b01110100 &
#487
0#
#488
1#
b01110101 &
#489
0#
#490
1#
b01110110 &
#491
0#
#492
1#
b01110111 &
#493
0#
#494
1#
b01111000 &
#495
0#
#496
1#
b01111001 &
#497
0#
#498
1#
b01111010 &
#499
0#
#500
1#
b01111011 &
#501
0#
#502
1#
b01111100 &
#503
0#
#504
1#
b01111101 &
#505
0#
#506
1#
b01111110 &
#507
0#
#508
1#
b01111111 &
#509
0#
#510
1#
b10000000 &
#511
0#
#512
1#
b10000001 &
#513
0#
#514
1#
b10000010 &
#515
0#
#516
1#
b10000011 &
#517
0#
#518
1#
b10000100 &
#519
0#
#520
1#
b10000101 &
#521
0#
#522
1#
b10000110 &
#523
0#
#524
1#
b10000111 &
#525
0#
#526
1#
b10001000 &
#527
0#
#528
1#
b10001001 &
#529
0#
#530
1#
b10001010 &
#531
0#
#532
1#
b10001011 &
#533
0#
#534
1#
b10001100 &
#535
0#
#536
1#
b10001101 &
#537
0#
#538
1#
b10001110 &
#539
0#
#540
1#
b10001111 &
#541
0#
#542
1#
b10010000 &
#543
0#
#544
1#
b10010001 &
#545
0#
#546
1#
b10010010 &
#547
0#
#548
1#
b10010011 &
#549
0#
#550
1#
b10010100 &
#551
0#
#552
1#
b10010101 &
#553
0#
#554
1#
b10010110 &
#555
0#
#556
1#
b10010111 &
#557
0#
#558
1#
0%
b10011000 &
#559
0#
#560
1#
b10010111 &
#561
0#
#562
1#
b10010110 &
#563
0#
#564
1#
b10010101 &
#565
0#
#566
1#
b10010100 &
#567
0#
#568
1#
b10010011 &
#569
0#
#570
1#
b10010010 &
#571
0#
#572
1#
b10010001 &
#573
0#
#574
1#
b10010000 &
#575
0#
#576
1#
b10001111 &
#577
0#
#578
1#
b10001110 &
#579
0#
#580
1#
b10001101 &
#581
0#
#582
1#
b10001100 &
#583
0#
#584
1#
b10001011 &
#585
0#
#586
1#
b10001010 &
#587
0#
#588
1#
b10001001 &
#589
0#
#590
1#
b10001000 &
#591
0#
#592
1#
b10000111 &
#593
0#
#594
1#
b10000110 &
#595
0#
#596
1#
b10000101 &
#597
0#
#598
1#
b10000100 &
#599
0#
#600
1#
b10000011 &
#601
0#
#602
1#
b10000010 &
#603
0#
#604
1#
b10000001 &
#605
0#
#606
1#
b10000000 &
#607
0#
#608
1#
b01111111 &
#609
0#
#610
1#
b01111110 &
#611
0#
#612
1#
b01111101 &
#613
0#
#614
1#
b01111100 &
#615
0#
#616
1#
b01111011 &
#617
0#
#618
1#
b01111010 &
#619
0#
#620
1#
b01111001 &
#621
0#
#622
1#
b01111000 &
#623
0#
#624
1#
b01110111 &
#625
0#
#626
1#
b01110110 &
#627
0#
#628
1#
b01110101 &
#629
0#
#630
1#
b01110100 &
#631
0#
#632
1#
b01110011 &
#633
0#
#634
1#
b01110010 &
#635
0#
#636
1#
b01110001 &
#637
0#
#638
1#
b01110000 &
#639
0#
#640
1#
b01101111 &
#641
0#
#642
1#
b01101110 &
#643
0#
#644
1#
b01101101 &
#645
0#
#646
1#
b01101100 &
#647
0#
#648
1#
b01101011 &
#649
0#
#650
1#
b01101010 &
#651
0#
#652
1#
b01101001 &
#653
0#
#654
1#
b01101000 &
#655
0#
#656
1#
b01100111 &
#657
0#
#658
1#
b01100110 &
#659
0#
#660
1#
b01100101 &
#661
0#
#662
1#
b01100100 &
#663
0#
#664
1#
b01100011 &
#665
0#
#666
1#
b01100010 &
#667
0#
#668
1#
b01100001 &
#669
0#
#670
1#
b01100000 &
#671
0#
#672
1#
b01011111 &
#673
0#
#674
1#
b01011110 &
#675
0#
#676
1#
b01011101 &
#677
0#
#678
1#
b01011100 &
#679
0#
#680
1#
b01011011 &
#681
0#
#682
1#
b01011010 &
#683
0#
#684
1#
b01011001 &
#685
0#
#686
1#
b01011000 &
#687
0#
#688
1#
b01010111 &
#689
0#
#690
1#
b01010110 &
#691
0#
#692
1#
b01010101 &
#693
0#
#694
1#
b01010100 &
#695
0#
#696
1#
b01010011 &
#697
0#
#698
1#
b01010010 &
#699
0#
#700
1#
b01010001 &
#701
0#
#702
1#
b01010000 &
#703
0#
#704
1#
b01001111 &
#705
0#
#706
1#
b01001110 &
#707
0#
#708
1#
b01001101 &
#709
0#
#710
1#
b01001100 &
#711
0#
#712
1#
b01001011 &
#713
0#
#714
1#
b01001010 &
#715
0#
#716
1#
b01001001 &
#717
0#
#718
1#
b01001000 &
#719
0#
#720
1#
b01000111 &
#721
0#
#722
1#
b01000110 &
#723
0#
#724
1#
b01000101 &
#725
0#
#726
1#
b01000100 &
#727
0#
#728
1#
b01000011 &
#729
0#
#730
1#
b01000010 &
#731
0#
#732
1#
b01000001 &
#733
0#
#734
1#
b01000000 &
#735
0#
#736
1#
b00111111 &
#737
0#
#738
1#
b00111110 &
#739
0#
#740
1#
b00111101 &
#741
0#
#742
1#
b00111100 &
#743
0#
#744
1#
b00111011 &
#745
0#
#746
1#
b00111010 &
#747
0#
#748
1#
b00111001 &
#749
0#
#750
1#
b00111000 &
#751
0#
#752
1#
b00110111 &
#753
0#
#754
1#
b00110110 &
#755
0#
#756
1#
b00110101 &
#757
0#
#758
1#
b00110100 &
#759
0#
#760
1#
b00110011 &
#761
0#
#762
1#
b00110010 &
#763
0#
#764
1#
b00110001 &
#765
0#
#766
1#
b00110000 &
#767
0#
#768
1#
b00101111 &
#769
0#
#770
1#
b00101110 &
#771
0#
#772
1#
b00101101 &
#773
0#
#774
1#
b00101100 &
#775
0#
#776
1#
b00101011 &
#777
0#
#778
1#
b00101010 &
#779
0#
#780
1#
b00101001 &
#781
0#
#782
1#
b00101000 &
#783
0#
#784
1#
b00100111 &
#785
0#
#786
1#
b00100110 &
#787
0#
#788
1#
b00100101 &
#789
0#
#790
1#
b00100100 &
#791
0#
#792
1#
b00100011 &
#793
0#
#794
1#
b00100010 &
#795
0#
#796
1#
b00100001 &
#797
0#
#798
1#
b00100000 &
#799
0#
#800
1#
b00011111 &
#801
0#
#802
1#
b00011110 &
#803
0#
#804
1#
b00011101 &
#805
0#
#806
1#
b00011100 &
#807
0#
#808
1#
b00011011 &
#809
0#
#810
1#
b00011010 &
#811
0#
#812
1#
b00011001 &
#813
0#
#814
1#
b00011000 &
#815
0#
#816
1#
b00010111 &
#817
0#
#818
1#
b00010110 &
#819
0#
#820
1#
b00010101 &
#821
0#
#822
1#
b00010100 &
#823
0#
#824
1#
b00010011 &
#825
0#
#826
1#
b00010010 &
#827
0#
#828
1#
b00010001 &
#829
0#
#830
1#
b00010000 &
#831
0#
#832
1#
b00001111 &
#833
0#
#834
1#
b00001110 &
#835
0#
#836
1#
b00001101 &
#837
0#
#838
1#
b00001100 &
#839
0#
#840
1#
b00001011 &
#841
0#
#842
1#
b00001010 &
#843
0#
#844
1#
b00001001 &
#845
0#
#846
1#
b00001000 &
#847
0#
#848
1#
b00000111 &
#849
0#
#850
1#
b00000110 &
#851
0#
#852
1#
b00000101 &
#853
0#
#854
1#
b00000100 &
#855
0#
#856
1#
b00000011 &
#857
0#
#858
1#
b00000010 &
#859
0#
#860
1#
b00000001 &
#861
0#
#862
1#
b00000000 &
#863
0#
#864
1#
b11111111 &
#865
0#
#866
1#
b11111110 &
#867
0#
#868
1#
b11111101 &
#869
0#
#870
1#
b11111100 &
#871
0#
#872
1#
b11111011 &
#873
0#
#874
1#
b11111010 &
#875
0#
#876
1#
b11111001 &
#877
0#
#878
1#
b11111000 &
#879
0#
#880
1#
b11110111 &
#881
0#
#882
1#
b11110110 &
#883
0#
#884
1#
b11110101 &
#885
0#
#886
1#
b11110100 &
#887
0#
#888
1#
b11110011 &
#889
0#
#890
1#
b11110010 &
#891
0#
#892
1#
b11110001 &
#893
0#
#894
1#
b11110000 &
#895
0#
#896
1#
b11101111 &
#897
0#
#898
1#
b11101110 &
#899
0#
#900
1#
b11101101 &
#901
0#
#902
1#
b11101100 &
#903
0#
#904
1#
b11101011 &
#905
0#
#906
1#
b11101010 &
#907
0#
#908
1#
b11101001 &
#909
0#
#910
1#
b11101000 &
#911
0#
#912
1#
b11100111 &
#913
0#
#914
1#
b11100110 &
#915
0#
#916
1#
b11100101 &
#917
0#
#918
1#
b11100100 &
#919
0#
#920
1#
b11100011 &
#921
0#
#922
1#
b11100010 &
#923
0#
#924
1#
b11100001 &
#925
0#
#926
1#
b11100000 &
#927
0#
#928
1#
b11011111 &
#929
0#
#930
1#
b11011110 &
#931
0#
#932
1#
b11011101 &
#933
0#
#934
1#
b11011100 &
#935
0#
#936
1#
b11011011 &
#937
0#
#938
1#
b11011010 &
#939
0#
#940
1#
b11011001 &
#941
0#
#942
1#
b11011000 &
#943
0#
#944
1#
b11010111 &
#945
0#
#946
1#
b11010110 &
#947
0#
#948
1#
b11010101 &
#949
0#
#950
1#
b11010100 &
#951
0#
#952
1#
b11010011 &
#953
0#
#954
1#
b11010010 &
#955
0#
#956
1#
b11010001 &
#957
0#
#958
1#
b11010000 &
#959
0#
#960
1#
b11001111 &
#961
0#
#962
1#
b11001110 &
#963
0#
#964
1#
b11001101 &
#965
0#
#966
1#
b11001100 &
#967
0#
#968
1#
b11001011 &
#969
0#
#970
1#
b11001010 &
#971
0#
#972
1#
b11001001 &
#973
0#
#974
1#
b11001000 &
#975
0#
#976
1#
b11000111 &
#977
0#
#978
1#
b11000110 &
#979
0#
#980
1#
b11000101 &
#981
0#
#982
1#
b11000100 &
#983
0#
#984
1#
b11000011 &
#985
0#
#986
1#
b11000010 &
#987
0#
#988
1#
b11000001 &
#989
0#
#990
1#
b11000000 &
#991
0#
#992
1#
b10111111 &
#993
0#
#994
1#
b10111110 &
#995
0#
#996
1#
b10111101 &
#997
0#
#998
1#
b10111100 &
